{
	"cli": true,
	"target": "directory",
	"adapterName": "bascloud",
	"title": "BAScloud",
	"expert": "no",
	"features": [
		"adapter"
	],
	"adminFeatures": [],
	"type": "communication",
	"startMode": "daemon",
	"connectionType": "cloud",
	"dataSource": "poll",
	"connectionIndicator": "no",
	"language": "TypeScript",
	"nodeVersion": "18",
	"adminUi": "json",
	"tools": [
		"ESLint"
	],
	"releaseScript": "yes",
	"devServer": "yes",
	"devServerPort": 8081,
	"indentation": "Tab",
	"quotes": "single",
	"authorName": "Yanick",
	"authorGithub": "BAScloud",
	"authorEmail": "stephan@bascloud.net",
	"gitRemoteProtocol": "HTTPS",
	"gitCommit": "no",
	"defaultBranch": "main",
	"license": "MIT License",
	"dependabot": "yes",
	"creatorVersion": "2.6.2"
}