{
  "common": {
    "name": "bascloud",
    "version": "0.1.1",
    "news": {
      "0.1.1": {
        "en": "small fixes, add build folder",
        "de": "Kleine Korrekturen, Build-Ordner hinzufügen",
        "ru": "небольшие исправления, добавлена ​​папка сборки",
        "pt": "pequenas correções, adicione pasta de compilação",
        "nl": "kleine oplossingen, voeg een build-map toe",
        "fr": "petites corrections, ajouter un dossier de construction",
        "it": "piccole correzioni, aggiunta della cartella di build",
        "es": "pequeñas correcciones, agregar carpeta de compilación",
        "pl": "małe poprawki, dodaj folder kompilacji",
        "uk": "невеликі виправлення, додайте папку збірки",
        "zh-cn": "小修复，添加构建文件夹"
      },
      "0.1.0": {
        "en": "initial release",
        "de": "Erstveröffentlichung",
        "ru": "Начальная версия",
        "pt": "lançamento inicial",
        "nl": "Eerste uitgave",
        "fr": "Première version",
        "it": "Versione iniziale",
        "es": "Versión inicial",
        "pl": "Pierwsze wydanie",
        "uk": "Початкова версія",
        "zh-cn": "首次出版"
      }
    },
    "titleLang": {
      "en": "BAScloud",
      "de": "BAScloud",
      "ru": "BAScloud",
      "pt": "BAScloud",
      "nl": "BAScloud",
      "fr": "BAScloud",
      "it": "BAScloud",
      "es": "BAScloud",
      "pl": "BAScloud",
      "uk": "BAScloud",
      "zh-cn": "BAScloud"
    },
    "desc": {
      "en": "BAScloud is a secure platform for networking and storing building information across properties.",
      "de": "BAScloud ist eine sichere Plattform zur objektübergreifenden Vernetzung und Speicherung von Gebäudeinformationen.",
      "ru": "BAScloud — это безопасная платформа для создания сети и хранения информации о зданиях на разных объектах.",
      "pt": "BAScloud é uma plataforma segura para rede e armazenamento de informações prediais em propriedades.",
      "nl": "BAScloud is een veilig platform voor het netwerken en opslaan van gebouwinformatie over verschillende eigendommen heen.",
      "fr": "BAScloud est une plate-forme sécurisée pour la mise en réseau et le stockage des informations sur les bâtiments dans toutes les propriétés.",
      "it": "BAScloud è una piattaforma sicura per il networking e l'archiviazione di informazioni sugli edifici tra proprietà.",
      "es": "BAScloud es una plataforma segura para establecer contactos y almacenar información de construcción en todas las propiedades.",
      "pl": "BAScloud to bezpieczna platforma do łączenia w sieć i przechowywania informacji o budynkach w różnych obiektach.",
      "uk": "BAScloud — це безпечна платформа для роботи в мережі та зберігання інформації про будівлі в об’єктах.",
      "zh-cn": "BAScloud 是一个安全平台，用于跨物业联网和存储建筑信息。"
    },
    "authors": [
      "Yanick Stephan <stephan@bascloud.net>"
    ],
    "keywords": [
      "bascloud",
      "digital twin",
      "building automation",
      "smart building",
      "iot",
      "connector"
    ],
    "license": "MIT",
    "licenseInformation": {
      "type": "free",
      "license": "MIT"
    },
    "platform": "Javascript/Node.js",
    "main": "build/main.js",
    "nogit": true,
    "icon": "bascloud.png",
    "enabled": true,
    "extIcon": "https://raw.githubusercontent.com/BAScloud/ioBroker.bascloud/main/admin/bascloud.png",
    "readme": "https://github.com/BAScloud/ioBroker.bascloud/blob/main/README.md",
    "loglevel": "info",
    "tier": 3,
    "mode": "daemon",
    "type": "communication",
    "compact": true,
    "connectionType": "cloud",
    "dataSource": "poll",
    "adminUI": {
      "config": "json"
    },
    "dependencies": [
      {
        "js-controller": ">=3.3.22"
      }
    ],
    "globalDependencies": [
      {
        "admin": ">=5.1.13"
      }
    ]
  },
  "native": {
    "tenantId": "",
    "apiKey": "",
    "readingsWrite": [],
    "readingsRead": []
  },
  "objects": [],
  "instanceObjects": []
}
